{"type":"FeatureCollection", "features": [
{"type":"Feature","geometry":{"type":"Point","coordinates":[89.14043550000008,26.60334800000004,0]},"properties":{"OID_":0,"Name":"Sri Sri Jateswar Temple - Hindu temple","FolderPath":"religious1.kml/religious","SymbolID":0,"AltMode":-1,"Base":0,"Snippet":"","PopupInfo":"J43R+85M\nPMGSY Rd\nJateshwar, West Bengal 735216","HasLabel":-1,"LabelID":0,"Photo":"D:\\disertation(tourist_spot)\\work in alipurduar (last)\\ALIPURDUAR\\IMAGE\\RELIGIOUS\\Sri Sri Jateswar Temple - Hindu temple.jpeg"}},
{"type":"Feature","geometry":{"type":"Point","coordinates":[89.54074220000007,26.491700000000037,0]},"properties":{"OID_":0,"Name":"Radha Madhab Temple","FolderPath":"religious1.kml/religious","SymbolID":0,"AltMode":-1,"Base":0,"Snippet":"","PopupInfo":"FGRR+M8F\nAlipurduar, West Bengal 736121\n\nClosed ⋅ Opens 8 am","HasLabel":-1,"LabelID":0,"Photo":"D:\\disertation(tourist_spot)\\work in alipurduar (last)\\ALIPURDUAR\\IMAGE\\RELIGIOUS\\Radha Madhab Temple.jpeg"}},
{"type":"Feature","geometry":{"type":"Point","coordinates":[89.70321670000004,26.51949120000006,0]},"properties":{"OID_":0,"Name":"Little flock church","FolderPath":"religious1.kml/religious","SymbolID":0,"AltMode":-1,"Base":0,"Snippet":"","PopupInfo":"Church\nGP93+Q7V\nBara Chakibas, West Bengal 736206","HasLabel":-1,"LabelID":0,"Photo":"D:\\disertation(tourist_spot)\\work in alipurduar (last)\\ALIPURDUAR\\IMAGE\\RELIGIOUS\\Little flock church.jpeg"}}
]}